multicommand.py
multicommand-2.0.1.dist-info/METADATA
multicommand-2.0.1.dist-info/WHEEL
multicommand-2.0.1.dist-info/licenses/LICENSE
multicommand-2.0.1.dist-info/RECORD
