Metadata-Version: 2.4
Name: multicommand
Version: 2.0.1
Summary: Simple subcommand CLIs with argparse
Project-URL: Homepage, https://github.com/andrewrosss/multicommand
Project-URL: Repository, https://github.com/andrewrosss/multicommand
Project-URL: Documentation, https://multicommand.vercel.app
Author-email: Andrew Ross <andrew.ross.mail@gmail.com>
License: MIT
License-File: LICENSE
Keywords: argparse,cli,commands,subcommands,tool
Classifier: Environment :: Console
Classifier: Intended Audience :: Developers
Classifier: License :: OSI Approved :: MIT License
Classifier: Operating System :: OS Independent
Classifier: Programming Language :: Python :: 3.10
Classifier: Programming Language :: Python :: 3.11
Classifier: Programming Language :: Python :: 3.12
Classifier: Programming Language :: Python :: 3.13
Classifier: Topic :: Software Development :: Libraries :: Python Modules
Classifier: Topic :: Software Development :: User Interfaces
Classifier: Topic :: Utilities
Classifier: Typing :: Typed
Requires-Python: >=3.10
